{
  "data": {
    "players": {
      "cbebe": 105,
      "hughjanusonly": 7,
      "hugh-jazz": 40,
      "JRetza": 8,
      "thedoodler": 4,
      "minji-o-j": 1
    },
    "totalGames": 4,
    "wins": {
      "top": 4,
      "bot": 0,
      "draw": 0
    },
    "totalMoves": 169,
    "mostRecentMoves": [
      {
        "name": "cbebe",
        "side": "top",
        "idx": 6
      },
      {
        "name": "cbebe",
        "side": "bot",
        "idx": 1
      },
      {
        "name": "JRetza",
        "side": "top",
        "idx": -1
      }
    ],
    "mostRecentGames": [
      {
        "scores": {
          "top": 54,
          "bot": 44
        },
        "turnsPlayed": 21
      },
      {
        "scores": {
          "top": 57,
          "bot": 41
        },
        "turnsPlayed": 11
      },
      {
        "scores": {
          "top": 61,
          "bot": 37
        },
        "turnsPlayed": 69
      }
    ]
  },
  "board": {
    "currentTurn": "top",
    "top": [
      1,
      10,
      7,
      1,
      2,
      9,
      0
    ],
    "bot": [
      5,
      5,
      25,
      1,
      0,
      4,
      3
    ],
    "scores": {
      "top": 17,
      "bot": 8
    },
    "gameOver": false,
    "turnsPlayed": 4
  }
}
